[{"17BT30030": [[{"subno": "CY11001", "subname": "CHEMISTRY", "ltp": "3-1-0 ", "crd": "4", "sub_type": "Depth", "grade": "D", "semno": "1"}, {"subno": "CY19001", "subname": "CHEMISTRY LAB.", "ltp": "0-0-3 ", "crd": "2", "sub_type": "Depth", "grade": "A", "semno": "1"}, {"subno": "EA10001", "subname": "EXTRA ACADEMIC ACTIVITY-I", "ltp": "0-0-3 ", "crd": "0", "sub_type": "Depth", "grade": "Y", "semno": "1"}, {"subno": "EA10005", "subname": "INDUCTION PROGRAM", "ltp": "0-0-0", "crd": "0", "sub_type": "Depth", "grade": "Y", "semno": "1"}, {"subno": "EE11001", "subname": "ELECTRICAL TECHNOLOGY", "ltp": "3-1-0 ", "crd": "4", "sub_type": "Depth", "grade": "P", "semno": "1"}, {"subno": "EE19001", "subname": "ELECTRICAL TECHNOLOGY LAB.", "ltp": "0-0-3 ", "crd": "2", "sub_type": "Depth", "grade": "B", "semno": "1"}, {"subno": "HS13001", "subname": "ENGLISH FOR COMMUNICATION", "ltp": "3-0-2 ", "crd": "4", "sub_type": "Depth", "grade": "D", "semno": "1"}, {"subno": "MA10001", "subname": "MATHEMATICS-I", "ltp": "3-1-0 ", "crd": "4", "sub_type": "Depth", "grade": "P", "semno": "1"}, {"subno": "ME19001", "subname": "INTRODUCTION TO MANUFACTURING PROCESSES", "ltp": "0-0-3 ", "crd": "2", "sub_type": "Depth", "grade": "B", "semno": "1"}, {"subno": "CE13001", "subname": "ENGINEERING DRAWING AND COMPUTER GRAPHICS", "ltp": "1-0-3 ", "crd": "3", "sub_type": "Depth", "grade": "D", "semno": "2"}, {"subno": "CS10001", "subname": "PROGRAMMING AND DATA STRUCTURES", "ltp": "3-0-0", "crd": "3", "sub_type": "Depth", "grade": "D", "semno": "2"}, {"subno": "CS19101", "subname": "PROGRAMMING AND DATA STRUCTURES TUTORIAL AND LABORATORY", "ltp": "0-1-3", "crd": "3", "sub_type": "Depth", "grade": "D", "semno": "2"}, {"subno": "EA10002", "subname": "EXTRA ACADEMIC ACTIVITY-II", "ltp": "0-0-3 ", "crd": "0", "sub_type": "Depth", "grade": "Y", "semno": "2"}, {"subno": "MA10002", "subname": "MATHEMATICS-II", "ltp": "3-1-0 ", "crd": "4", "sub_type": "Depth", "grade": "D", "semno": "2"}, {"subno": "ME10001", "subname": "MECHANICS", "ltp": "3-1-0 ", "crd": "4", "sub_type": "Depth", "grade": "P", "semno": "2"}, {"subno": "PH11001", "subname": "PHYSICS", "ltp": "3-1-0 ", "crd": "4", "sub_type": "Depth", "grade": "A", "semno": "2"}, {"subno": "PH19001", "subname": "PHYSICS LAB.", "ltp": "0-0-3 ", "crd": "2", "sub_type": "Depth", "grade": "A", "semno": "2"}, {"subno": "BS20001", "subname": "SCIENCE OF LIVING SYSTEM", "ltp": "2-0-0     ", "crd": "2", "sub_type": "Depth", "grade": "B", "semno": "3"}, {"subno": "BT20103", "subname": "MICROBIOLOGY", "ltp": "3-0-0 ", "crd": "3", "sub_type": "Depth", "grade": "A", "semno": "3"}, {"subno": "BT21101", "subname": "BIOCHEMISTRY", "ltp": "3-1-0 ", "crd": "4", "sub_type": "Depth", "grade": "B", "semno": "3"}, {"subno": "BT21105", "subname": "BIOCHEM. REACTION ENGG. AND BIOENERGETICS", "ltp": "3-1-0 ", "crd": "4", "sub_type": "Depth", "grade": "A", "semno": "3"}, {"subno": "BT29001", "subname": "BIOCHEMISTRY LABORATORY", "ltp": "0-0-3 ", "crd": "2", "sub_type": "Depth", "grade": "EX", "semno": "3"}, {"subno": "BT29003", "subname": "MICROBIOLOGY LABORATORY", "ltp": "0-0-3 ", "crd": "2", "sub_type": "Depth", "grade": "A", "semno": "3"}, {"subno": "EA10003", "subname": "EXTRA ACADEMIC ACTIVITY-III", "ltp": "0-0-3 ", "crd": "0", "sub_type": "Depth", "grade": "C", "semno": "3"}, {"subno": "EV20001", "subname": "ENVIRONMENTAL SCIENCE", "ltp": "2-0-0     ", "crd": "2", "sub_type": "Depth", "grade": "EX", "semno": "3"}, {"subno": "MA20103", "subname": "PARTIAL DIFFERENTIAL EQUATIONS", "ltp": "3-0-0 ", "crd": "3", "sub_type": "Depth", "grade": "C", "semno": "3"}, {"subno": "BT21002", "subname": "CELL & MOLECULAR BIOLOGY", "ltp": "3-1-0 ", "crd": "4", "sub_type": "Depth", "grade": "A", "semno": "4"}, {"subno": "BT29002", "subname": "CELL & MOLECULAR BIOLOGY LABORATORY", "ltp": "0-0-3 ", "crd": "2", "sub_type": "Depth", "grade": "A", "semno": "4"}, {"subno": "EA10004", "subname": "EXTRA ACADEMIC ACTIVITY-IV", "ltp": "0-0-3 ", "crd": "0", "sub_type": "Depth", "grade": "A", "semno": "4"}, {"subno": "EC21101", "subname": "BASIC ELECTRONICS", "ltp": "3-1-0 ", "crd": "4", "sub_type": "Depth", "grade": "C", "semno": "4"}, {"subno": "EC29001", "subname": "BASIC ELECTRONICS LAB.", "ltp": "0-0-3 ", "crd": "2", "sub_type": "Depth", "grade": "B", "semno": "4"}, {"subno": "HS20001", "subname": "ECONOMICS", "ltp": "3-1-0 ", "crd": "4", "sub_type": "Depth", "grade": "B", "semno": "4"}, {"subno": "HS60044", "subname": "", "ltp": "", "crd": "", "sub_type": "HSS", "grade": "C", "semno": "4"}, {"subno": "MA20104", "subname": "PROBABILITY & STATISTICS", "ltp": "3-0-0 ", "crd": "3", "sub_type": "Depth", "grade": "D", "semno": "4"}, {"subno": "BT31009", "subname": "GENETICS", "ltp": "3-1-0", "crd": "4", "sub_type": "Depth", "grade": "C", "semno": "5"}, {"subno": "BT31011", "subname": "ENVIRONMENTAL BIOTECHNOLOGY", "ltp": "3-1-0", "crd": "4", "sub_type": "Depth", "grade": "B", "semno": "5"}, {"subno": "BT39001", "subname": "ANALYTICAL BIOCHEMISTRY LABORATORY", "ltp": "0-0-3 ", "crd": "2", "sub_type": "Depth", "grade": "B", "semno": "5"}, {"subno": "BT39003", "subname": "BIOCHEMICAL ENGGINEERING LABORATORY", "ltp": "0-0-3", "crd": "2", "sub_type": "Depth", "grade": "B", "semno": "5"}, {"subno": "CH21103", "subname": "CHEMICAL PROCESS CALCULATIONS", "ltp": "3-1-0 ", "crd": "4", "sub_type": "Depth", "grade": "P", "semno": "5"}, {"subno": "CH31001", "subname": "MASS TRANSFER I", "ltp": "3-1-0 ", "crd": "4", "sub_type": "Depth", "grade": "D", "semno": "5"}, {"subno": "EP60044", "subname": "", "ltp": "", "crd": "", "sub_type": "IEM", "grade": "B", "semno": "5"}, {"subno": "BT31006", "subname": "BIOINFORMATICS", "ltp": "3-0-0 ", "crd": "3", "sub_type": "Depth", "grade": "B", "semno": "6"}, {"subno": "BT31010", "subname": "PLANT CELL TISSUE CULTURE", "ltp": "3-1-0", "crd": "4", "sub_type": "Depth", "grade": "EX", "semno": "6"}, {"subno": "BT31014", "subname": "IMMUNOLOGY", "ltp": "3-1-0 ", "crd": "4", "sub_type": "Depth", "grade": "EX", "semno": "6"}, {"subno": "BT39006", "subname": "PLANT CELL & TISSUE CULTURE LABORATORY", "ltp": "0-0-3 ", "crd": "2", "sub_type": "Depth", "grade": "A", "semno": "6"}, {"subno": "BT39008", "subname": "BIOINFORMATICS LABORATORY", "ltp": "0-0-3 ", "crd": "2", "sub_type": "Depth", "grade": "B", "semno": "6"}, {"subno": "BT61030", "subname": "", "ltp": "", "crd": "", "sub_type": "Depth", "grade": "EX", "semno": "6"}, {"subno": "CH39006", "subname": "MASS TRANSFER LABORATORY", "ltp": "0-0-3 ", "crd": "2", "sub_type": "Depth", "grade": "A", "semno": "6"}, {"subno": "BT40009", "subname": "BIOPROCESS TECHNOLOGY", "ltp": "3-1-0 ", "crd": "4", "sub_type": "Depth", "grade": "A", "semno": "7"}, {"subno": "BT47007", "subname": "PROJECT-I", "ltp": "0-0-0", "crd": "3", "sub_type": "Project-I", "grade": "A", "semno": "7"}, {"subno": "BT49001", "subname": "ENZYME TECHNOLOGY LABORATORY", "ltp": "0-0-3", "crd": "2", "sub_type": "Depth", "grade": "I", "semno": "7"}, {"subno": "BT63027", "subname": "", "ltp": "", "crd": "", "sub_type": "Elective I (PG)", "grade": "B", "semno": "7"}, {"subno": "ES60004", "subname": "", "ltp": "", "crd": "", "sub_type": "IT", "grade": "A", "semno": "7"}, {"subno": "MM60009", "subname": "", "ltp": "", "crd": "", "sub_type": "Elective II (PG)", "grade": "C", "semno": "7"}, {"subno": "BT41012", "subname": "DOWNSTREAM PROCESSING", "ltp": "3-0-0 ", "crd": "3", "sub_type": "Elective III", "grade": "A", "semno": "8"}, {"subno": "BT41022", "subname": "NEUROPHYSIOLOGY", "ltp": "3-1-0 ", "crd": "4", "sub_type": "Depth", "grade": "A", "semno": "8"}, {"subno": "BT47006", "subname": "PROJECT - PART 2", "ltp": "0-0-9 ", "crd": "6", "sub_type": "Project-II", "grade": "", "semno": "8"}, {"subno": "BT60004", "subname": "", "ltp": "", "crd": "", "sub_type": "Elective VI (PG)", "grade": "A", "semno": "8"}, {"subno": "BT60016", "subname": "", "ltp": "", "crd": "", "sub_type": "Elective V (PG)", "grade": "B", "semno": "8"}, {"subno": "MM72335", "subname": "", "ltp": "", "crd": "", "sub_type": "Elective IV", "grade": "A", "semno": "8"}], [{"rollno": "17BT30030", "semno": "1", "sctscc": "22 - 22", "tcttcc": "22 - 22", "nccgsg": "6.27 - 6.27 - 6.27", "asctascc": "0 - 0", "acgasg": "0.00 - 0.00", "atctatcc": "0 - 0"}, {"rollno": "17BT30030", "semno": "2", "sctscc": "23 - 23", "tcttcc": "45 - 45", "nccgsg": "6.44 - 6.44 - 6.61", "asctascc": "0 - 0", "acgasg": "0.00 - 0.00", "atctatcc": "0 - 0"}, {"rollno": "17BT30030", "semno": "3", "sctscc": "22 - 22", "tcttcc": "67 - 67", "nccgsg": "7.16 - 7.16 - 8.64", "asctascc": "0 - 0", "acgasg": "0.00 - 0.00", "atctatcc": "0 - 0"}, {"rollno": "17BT30030", "semno": "4", "sctscc": "22 - 22", "tcttcc": "89 - 89", "nccgsg": "7.29 - 7.29 - 7.68", "asctascc": "0 - 0", "acgasg": "0.00 - 0.00", "atctatcc": "0 - 0"}, {"rollno": "17BT30030", "semno": "5", "sctscc": "23 - 23", "tcttcc": "112 - 112", "nccgsg": "7.22 - 7.22 - 6.96", "asctascc": "0 - 0", "acgasg": "0.00 - 0.00", "atctatcc": "0 - 0"}, {"rollno": "17BT30030", "semno": "6", "sctscc": "20 - 20", "tcttcc": "132 - 132", "nccgsg": "7.54 - 7.54 - 9.30", "asctascc": "0 - 0", "acgasg": "0.00 - 0.00", "atctatcc": "0 - 0"}, {"rollno": "17BT30030", "semno": "7", "sctscc": "17 - 17", "tcttcc": "149 - 149", "nccgsg": "7.64 - 7.64 - 8.47", "asctascc": "0 - 0", "acgasg": "0.00 - 0.00", "atctatcc": "0 - 0"}, {"rollno": "17BT30030", "semno": "8", "sctscc": "23 - 17", "tcttcc": "172 - 166", "nccgsg": "7.49 - 7.49 - 6.52", "asctascc": "0 - 0", "acgasg": "0.00 - 0.00", "atctatcc": "0 - 0"}]]}, {"17BT30005": [[{"subno": "CE13001", "subname": "ENGINEERING DRAWING AND COMPUTER GRAPHICS", "ltp": "1-0-3 ", "crd": "3", "sub_type": "Depth", "grade": "P", "semno": "1"}, {"subno": "CS10001", "subname": "PROGRAMMING AND DATA STRUCTURES", "ltp": "3-0-0", "crd": "3", "sub_type": "Depth", "grade": "D", "semno": "1"}, {"subno": "CS19101", "subname": "PROGRAMMING AND DATA STRUCTURES TUTORIAL AND LABORATORY", "ltp": "0-1-3", "crd": "3", "sub_type": "Depth", "grade": "P", "semno": "1"}, {"subno": "EA10001", "subname": "EXTRA ACADEMIC ACTIVITY-I", "ltp": "0-0-3 ", "crd": "0", "sub_type": "Depth", "grade": "Y", "semno": "1"}, {"subno": "EA10005", "subname": "INDUCTION PROGRAM", "ltp": "0-0-0", "crd": "0", "sub_type": "Depth", "grade": "Y", "semno": "1"}, {"subno": "MA10001", "subname": "MATHEMATICS-I", "ltp": "3-1-0 ", "crd": "4", "sub_type": "Depth", "grade": "P", "semno": "1"}, {"subno": "ME10001", "subname": "MECHANICS", "ltp": "3-1-0 ", "crd": "4", "sub_type": "Depth", "grade": "P", "semno": "1"}, {"subno": "PH11001", "subname": "PHYSICS", "ltp": "3-1-0 ", "crd": "4", "sub_type": "Depth", "grade": "P", "semno": "1"}, {"subno": "PH19001", "subname": "PHYSICS LAB.", "ltp": "0-0-3 ", "crd": "2", "sub_type": "Depth", "grade": "D", "semno": "1"}, {"subno": "CY11001", "subname": "CHEMISTRY", "ltp": "3-1-0 ", "crd": "4", "sub_type": "Depth", "grade": "D", "semno": "2"}, {"subno": "CY19001", "subname": "CHEMISTRY LAB.", "ltp": "0-0-3 ", "crd": "2", "sub_type": "Depth", "grade": "B", "semno": "2"}, {"subno": "EA10002", "subname": "EXTRA ACADEMIC ACTIVITY-II", "ltp": "0-0-3 ", "crd": "0", "sub_type": "Depth", "grade": "Y", "semno": "2"}, {"subno": "EE11001", "subname": "ELECTRICAL TECHNOLOGY", "ltp": "3-1-0 ", "crd": "4", "sub_type": "Depth", "grade": "P", "semno": "2"}, {"subno": "EE19001", "subname": "ELECTRICAL TECHNOLOGY LAB.", "ltp": "0-0-3 ", "crd": "2", "sub_type": "Depth", "grade": "D", "semno": "2"}, {"subno": "HS13001", "subname": "ENGLISH FOR COMMUNICATION", "ltp": "3-0-2 ", "crd": "4", "sub_type": "Depth", "grade": "C", "semno": "2"}, {"subno": "MA10002", "subname": "MATHEMATICS-II", "ltp": "3-1-0 ", "crd": "4", "sub_type": "Depth", "grade": "D", "semno": "2"}, {"subno": "ME19001", "subname": "INTRODUCTION TO MANUFACTURING PROCESSES", "ltp": "0-0-3 ", "crd": "2", "sub_type": "Depth", "grade": "B", "semno": "2"}, {"subno": "BS20001", "subname": "SCIENCE OF LIVING SYSTEM", "ltp": "2-0-0     ", "crd": "2", "sub_type": "Depth", "grade": "P", "semno": "3"}, {"subno": "BT20103", "subname": "MICROBIOLOGY", "ltp": "3-0-0 ", "crd": "3", "sub_type": "Depth", "grade": "C", "semno": "3"}, {"subno": "BT21101", "subname": "BIOCHEMISTRY", "ltp": "3-1-0 ", "crd": "4", "sub_type": "Depth", "grade": "D", "semno": "3"}, {"subno": "BT21105", "subname": "BIOCHEM. REACTION ENGG. AND BIOENERGETICS", "ltp": "3-1-0 ", "crd": "4", "sub_type": "Depth", "grade": "P", "semno": "3"}, {"subno": "BT29001", "subname": "BIOCHEMISTRY LABORATORY", "ltp": "0-0-3 ", "crd": "2", "sub_type": "Depth", "grade": "A", "semno": "3"}, {"subno": "BT29003", "subname": "MICROBIOLOGY LABORATORY", "ltp": "0-0-3 ", "crd": "2", "sub_type": "Depth", "grade": "B", "semno": "3"}, {"subno": "EA10003", "subname": "EXTRA ACADEMIC ACTIVITY-III", "ltp": "0-0-3 ", "crd": "0", "sub_type": "Depth", "grade": "C", "semno": "3"}, {"subno": "EV20001", "subname": "ENVIRONMENTAL SCIENCE", "ltp": "2-0-0     ", "crd": "2", "sub_type": "Depth", "grade": "C", "semno": "3"}, {"subno": "MA20103", "subname": "PARTIAL DIFFERENTIAL EQUATIONS", "ltp": "3-0-0 ", "crd": "3", "sub_type": "Depth", "grade": "P", "semno": "3"}, {"subno": "BT21002", "subname": "CELL & MOLECULAR BIOLOGY", "ltp": "3-1-0 ", "crd": "4", "sub_type": "Depth", "grade": "D", "semno": "4"}, {"subno": "BT29002", "subname": "CELL & MOLECULAR BIOLOGY LABORATORY", "ltp": "0-0-3 ", "crd": "2", "sub_type": "Depth", "grade": "B", "semno": "4"}, {"subno": "EA10004", "subname": "EXTRA ACADEMIC ACTIVITY-IV", "ltp": "0-0-3 ", "crd": "0", "sub_type": "Depth", "grade": "A", "semno": "4"}, {"subno": "EC21101", "subname": "BASIC ELECTRONICS", "ltp": "3-1-0 ", "crd": "4", "sub_type": "Depth", "grade": "P", "semno": "4"}, {"subno": "EC29001", "subname": "BASIC ELECTRONICS LAB.", "ltp": "0-0-3 ", "crd": "2", "sub_type": "Depth", "grade": "C", "semno": "4"}, {"subno": "HS20001", "subname": "ECONOMICS", "ltp": "3-1-0 ", "crd": "4", "sub_type": "Depth", "grade": "D", "semno": "4"}, {"subno": "HS60044", "subname": "", "ltp": "", "crd": "", "sub_type": "HSS", "grade": "D", "semno": "4"}, {"subno": "MA20104", "subname": "PROBABILITY & STATISTICS", "ltp": "3-0-0 ", "crd": "3", "sub_type": "Depth", "grade": "P", "semno": "4"}, {"subno": "BT31009", "subname": "GENETICS", "ltp": "3-1-0", "crd": "4", "sub_type": "Depth", "grade": "C", "semno": "5"}, {"subno": "BT31011", "subname": "ENVIRONMENTAL BIOTECHNOLOGY", "ltp": "3-1-0", "crd": "4", "sub_type": "Depth", "grade": "B", "semno": "5"}, {"subno": "BT39001", "subname": "ANALYTICAL BIOCHEMISTRY LABORATORY", "ltp": "0-0-3 ", "crd": "2", "sub_type": "Depth", "grade": "I", "semno": "5"}, {"subno": "BT39003", "subname": "BIOCHEMICAL ENGGINEERING LABORATORY", "ltp": "0-0-3", "crd": "2", "sub_type": "Depth", "grade": "B", "semno": "5"}, {"subno": "CH21103", "subname": "CHEMICAL PROCESS CALCULATIONS", "ltp": "3-1-0 ", "crd": "4", "sub_type": "Depth", "grade": "P", "semno": "5"}, {"subno": "CH31001", "subname": "MASS TRANSFER I", "ltp": "3-1-0 ", "crd": "4", "sub_type": "Depth", "grade": "P", "semno": "5"}, {"subno": "EP60038", "subname": "", "ltp": "", "crd": "", "sub_type": "IEM", "grade": "D", "semno": "5"}, {"subno": "BT31006", "subname": "BIOINFORMATICS", "ltp": "3-0-0 ", "crd": "3", "sub_type": "Depth", "grade": "C", "semno": "6"}, {"subno": "BT31010", "subname": "PLANT CELL TISSUE CULTURE", "ltp": "3-1-0", "crd": "4", "sub_type": "Depth", "grade": "A", "semno": "6"}, {"subno": "BT31014", "subname": "IMMUNOLOGY", "ltp": "3-1-0 ", "crd": "4", "sub_type": "Depth", "grade": "A", "semno": "6"}, {"subno": "BT39006", "subname": "PLANT CELL & TISSUE CULTURE LABORATORY", "ltp": "0-0-3 ", "crd": "2", "sub_type": "Depth", "grade": "A", "semno": "6"}, {"subno": "BT39008", "subname": "BIOINFORMATICS LABORATORY", "ltp": "0-0-3 ", "crd": "2", "sub_type": "Depth", "grade": "A", "semno": "6"}, {"subno": "BT61030", "subname": "", "ltp": "", "crd": "", "sub_type": "Depth", "grade": "A", "semno": "6"}, {"subno": "CH39006", "subname": "MASS TRANSFER LABORATORY", "ltp": "0-0-3 ", "crd": "2", "sub_type": "Depth", "grade": "A", "semno": "6"}, {"subno": "BS60003", "subname": "", "ltp": "", "crd": "", "sub_type": "Elective I (PG)", "grade": "A", "semno": "7"}, {"subno": "BT40009", "subname": "BIOPROCESS TECHNOLOGY", "ltp": "3-1-0 ", "crd": "4", "sub_type": "Depth", "grade": "B", "semno": "7"}, {"subno": "BT47007", "subname": "PROJECT-I", "ltp": "0-0-0", "crd": "3", "sub_type": "Project-I", "grade": "B", "semno": "7"}, {"subno": "BT49001", "subname": "ENZYME TECHNOLOGY LABORATORY", "ltp": "0-0-3", "crd": "2", "sub_type": "Depth", "grade": "I", "semno": "7"}, {"subno": "BT60015", "subname": "", "ltp": "", "crd": "", "sub_type": "Elective II (PG)", "grade": "A", "semno": "7"}, {"subno": "ES60004", "subname": "", "ltp": "", "crd": "", "sub_type": "IT", "grade": "A", "semno": "7"}, {"subno": "BT41012", "subname": "DOWNSTREAM PROCESSING", "ltp": "3-0-0 ", "crd": "3", "sub_type": "Elective IV", "grade": "B", "semno": "8"}, {"subno": "BT41022", "subname": "NEUROPHYSIOLOGY", "ltp": "3-1-0 ", "crd": "4", "sub_type": "Depth", "grade": "A", "semno": "8"}, {"subno": "BT47006", "subname": "PROJECT - PART 2", "ltp": "0-0-9 ", "crd": "6", "sub_type": "Project-II", "grade": "", "semno": "8"}, {"subno": "BT60004", "subname": "", "ltp": "", "crd": "", "sub_type": "Elective VI (PG)", "grade": "A", "semno": "8"}, {"subno": "BT60016", "subname": "", "ltp": "", "crd": "", "sub_type": "Elective V (PG)", "grade": "D", "semno": "8"}, {"subno": "MM72335", "subname": "", "ltp": "", "crd": "", "sub_type": "Elective III", "grade": "A", "semno": "8"}], [{"rollno": "17BT30005", "semno": "1", "sctscc": "23 - 23", "tcttcc": "23 - 23", "nccgsg": "5.22 - 5.22 - 5.22", "asctascc": "0 - 0", "acgasg": "0.00 - 0.00", "atctatcc": "0 - 0"}, {"rollno": "17BT30005", "semno": "2", "sctscc": "22 - 22", "tcttcc": "45 - 45", "nccgsg": "5.78 - 5.78 - 6.36", "asctascc": "0 - 0", "acgasg": "0.00 - 0.00", "atctatcc": "0 - 0"}, {"rollno": "17BT30005", "semno": "3", "sctscc": "22 - 22", "tcttcc": "67 - 67", "nccgsg": "5.94 - 5.94 - 6.27", "asctascc": "0 - 0", "acgasg": "0.00 - 0.00", "atctatcc": "0 - 0"}, {"rollno": "17BT30005", "semno": "4", "sctscc": "22 - 22", "tcttcc": "89 - 89", "nccgsg": "5.94 - 5.94 - 5.95", "asctascc": "0 - 0", "acgasg": "0.00 - 0.00", "atctatcc": "0 - 0"}, {"rollno": "17BT30005", "semno": "5", "sctscc": "21 - 21", "tcttcc": "110 - 110", "nccgsg": "6.03 - 6.03 - 6.38", "asctascc": "0 - 0", "acgasg": "0.00 - 0.00", "atctatcc": "0 - 0"}, {"rollno": "17BT30005", "semno": "6", "sctscc": "20 - 20", "tcttcc": "130 - 130", "nccgsg": "6.44 - 6.44 - 8.70", "asctascc": "0 - 0", "acgasg": "0.00 - 0.00", "atctatcc": "0 - 0"}, {"rollno": "17BT30005", "semno": "7", "sctscc": "17 - 17", "tcttcc": "147 - 147", "nccgsg": "6.69 - 6.69 - 8.59", "asctascc": "0 - 0", "acgasg": "0.00 - 0.00", "atctatcc": "0 - 0"}, {"rollno": "17BT30005", "semno": "8", "sctscc": "23 - 17", "tcttcc": "170 - 164", "nccgsg": "6.61 - 6.61 - 6.13", "asctascc": "0 - 0", "acgasg": "0.00 - 0.00", "atctatcc": "0 - 0"}]]}, {"17BT30025": [[{"subno": "CE13001", "subname": "ENGINEERING DRAWING AND COMPUTER GRAPHICS", "ltp": "1-0-3 ", "crd": "3", "sub_type": "Depth", "grade": "A", "semno": "1"}, {"subno": "CS10001", "subname": "PROGRAMMING AND DATA STRUCTURES", "ltp": "3-0-0", "crd": "3", "sub_type": "Depth", "grade": "A", "semno": "1"}, {"subno": "CS19101", "subname": "PROGRAMMING AND DATA STRUCTURES TUTORIAL AND LABORATORY", "ltp": "0-1-3", "crd": "3", "sub_type": "Depth", "grade": "EX", "semno": "1"}, {"subno": "EA10001", "subname": "EXTRA ACADEMIC ACTIVITY-I", "ltp": "0-0-3 ", "crd": "0", "sub_type": "Depth", "grade": "Y", "semno": "1"}, {"subno": "EA10005", "subname": "INDUCTION PROGRAM", "ltp": "0-0-0", "crd": "0", "sub_type": "Depth", "grade": "Y", "semno": "1"}, {"subno": "MA10001", "subname": "MATHEMATICS-I", "ltp": "3-1-0 ", "crd": "4", "sub_type": "Depth", "grade": "B", "semno": "1"}, {"subno": "ME10001", "subname": "MECHANICS", "ltp": "3-1-0 ", "crd": "4", "sub_type": "Depth", "grade": "A", "semno": "1"}, {"subno": "PH11001", "subname": "PHYSICS", "ltp": "3-1-0 ", "crd": "4", "sub_type": "Depth", "grade": "B", "semno": "1"}, {"subno": "PH19001", "subname": "PHYSICS LAB.", "ltp": "0-0-3 ", "crd": "2", "sub_type": "Depth", "grade": "A", "semno": "1"}, {"subno": "CY11001", "subname": "CHEMISTRY", "ltp": "3-1-0 ", "crd": "4", "sub_type": "Depth", "grade": "C", "semno": "2"}, {"subno": "CY19001", "subname": "CHEMISTRY LAB.", "ltp": "0-0-3 ", "crd": "2", "sub_type": "Depth", "grade": "A", "semno": "2"}, {"subno": "EA10002", "subname": "EXTRA ACADEMIC ACTIVITY-II", "ltp": "0-0-3 ", "crd": "0", "sub_type": "Depth", "grade": "Y", "semno": "2"}, {"subno": "EE11001", "subname": "ELECTRICAL TECHNOLOGY", "ltp": "3-1-0 ", "crd": "4", "sub_type": "Depth", "grade": "C", "semno": "2"}, {"subno": "EE19001", "subname": "ELECTRICAL TECHNOLOGY LAB.", "ltp": "0-0-3 ", "crd": "2", "sub_type": "Depth", "grade": "B", "semno": "2"}, {"subno": "HS13001", "subname": "ENGLISH FOR COMMUNICATION", "ltp": "3-0-2 ", "crd": "4", "sub_type": "Depth", "grade": "B", "semno": "2"}, {"subno": "MA10002", "subname": "MATHEMATICS-II", "ltp": "3-1-0 ", "crd": "4", "sub_type": "Depth", "grade": "B", "semno": "2"}, {"subno": "ME19001", "subname": "INTRODUCTION TO MANUFACTURING PROCESSES", "ltp": "0-0-3 ", "crd": "2", "sub_type": "Depth", "grade": "B", "semno": "2"}, {"subno": "BS20001", "subname": "SCIENCE OF LIVING SYSTEM", "ltp": "2-0-0     ", "crd": "2", "sub_type": "Depth", "grade": "C", "semno": "3"}, {"subno": "BT20103", "subname": "MICROBIOLOGY", "ltp": "3-0-0 ", "crd": "3", "sub_type": "Depth", "grade": "A", "semno": "3"}, {"subno": "BT21101", "subname": "BIOCHEMISTRY", "ltp": "3-1-0 ", "crd": "4", "sub_type": "Depth", "grade": "C", "semno": "3"}, {"subno": "BT21105", "subname": "BIOCHEM. REACTION ENGG. AND BIOENERGETICS", "ltp": "3-1-0 ", "crd": "4", "sub_type": "Depth", "grade": "B", "semno": "3"}, {"subno": "BT29001", "subname": "BIOCHEMISTRY LABORATORY", "ltp": "0-0-3 ", "crd": "2", "sub_type": "Depth", "grade": "EX", "semno": "3"}, {"subno": "BT29003", "subname": "MICROBIOLOGY LABORATORY", "ltp": "0-0-3 ", "crd": "2", "sub_type": "Depth", "grade": "A", "semno": "3"}, {"subno": "EA10003", "subname": "EXTRA ACADEMIC ACTIVITY-III", "ltp": "0-0-3 ", "crd": "0", "sub_type": "Depth", "grade": "P", "semno": "3"}, {"subno": "EV20001", "subname": "ENVIRONMENTAL SCIENCE", "ltp": "2-0-0     ", "crd": "2", "sub_type": "Depth", "grade": "A", "semno": "3"}, {"subno": "MA20103", "subname": "PARTIAL DIFFERENTIAL EQUATIONS", "ltp": "3-0-0 ", "crd": "3", "sub_type": "Depth", "grade": "C", "semno": "3"}, {"subno": "BT21002", "subname": "CELL & MOLECULAR BIOLOGY", "ltp": "3-1-0 ", "crd": "4", "sub_type": "Depth", "grade": "B", "semno": "4"}, {"subno": "BT29002", "subname": "CELL & MOLECULAR BIOLOGY LABORATORY", "ltp": "0-0-3 ", "crd": "2", "sub_type": "Depth", "grade": "A", "semno": "4"}, {"subno": "EA10004", "subname": "EXTRA ACADEMIC ACTIVITY-IV", "ltp": "0-0-3 ", "crd": "0", "sub_type": "Depth", "grade": "B", "semno": "4"}, {"subno": "EC21101", "subname": "BASIC ELECTRONICS", "ltp": "3-1-0 ", "crd": "4", "sub_type": "Depth", "grade": "B", "semno": "4"}, {"subno": "EC29001", "subname": "BASIC ELECTRONICS LAB.", "ltp": "0-0-3 ", "crd": "2", "sub_type": "Depth", "grade": "EX", "semno": "4"}, {"subno": "HS20001", "subname": "ECONOMICS", "ltp": "3-1-0 ", "crd": "4", "sub_type": "Depth", "grade": "B", "semno": "4"}, {"subno": "HS60044", "subname": "", "ltp": "", "crd": "", "sub_type": "HSS", "grade": "C", "semno": "4"}, {"subno": "MA20104", "subname": "PROBABILITY & STATISTICS", "ltp": "3-0-0 ", "crd": "3", "sub_type": "Depth", "grade": "B", "semno": "4"}, {"subno": "BT31009", "subname": "GENETICS", "ltp": "3-1-0", "crd": "4", "sub_type": "Depth", "grade": "A", "semno": "5"}, {"subno": "BT31011", "subname": "ENVIRONMENTAL BIOTECHNOLOGY", "ltp": "3-1-0", "crd": "4", "sub_type": "Depth", "grade": "A", "semno": "5"}, {"subno": "BT39001", "subname": "ANALYTICAL BIOCHEMISTRY LABORATORY", "ltp": "0-0-3 ", "crd": "2", "sub_type": "Depth", "grade": "B", "semno": "5"}, {"subno": "BT39003", "subname": "BIOCHEMICAL ENGGINEERING LABORATORY", "ltp": "0-0-3", "crd": "2", "sub_type": "Depth", "grade": "A", "semno": "5"}, {"subno": "CH21103", "subname": "CHEMICAL PROCESS CALCULATIONS", "ltp": "3-1-0 ", "crd": "4", "sub_type": "Depth", "grade": "C", "semno": "5"}, {"subno": "CH31001", "subname": "MASS TRANSFER I", "ltp": "3-1-0 ", "crd": "4", "sub_type": "Depth", "grade": "EX", "semno": "5"}, {"subno": "EP60007", "subname": "", "ltp": "", "crd": "", "sub_type": "IEM", "grade": "C", "semno": "5"}, {"subno": "BT31006", "subname": "BIOINFORMATICS", "ltp": "3-0-0 ", "crd": "3", "sub_type": "Depth", "grade": "B", "semno": "6"}, {"subno": "BT31010", "subname": "PLANT CELL TISSUE CULTURE", "ltp": "3-1-0", "crd": "4", "sub_type": "Depth", "grade": "C", "semno": "6"}, {"subno": "BT31014", "subname": "IMMUNOLOGY", "ltp": "3-1-0 ", "crd": "4", "sub_type": "Depth", "grade": "A", "semno": "6"}, {"subno": "BT39006", "subname": "PLANT CELL & TISSUE CULTURE LABORATORY", "ltp": "0-0-3 ", "crd": "2", "sub_type": "Depth", "grade": "A", "semno": "6"}, {"subno": "BT39008", "subname": "BIOINFORMATICS LABORATORY", "ltp": "0-0-3 ", "crd": "2", "sub_type": "Depth", "grade": "EX", "semno": "6"}, {"subno": "BT61030", "subname": "", "ltp": "", "crd": "", "sub_type": "Depth", "grade": "A", "semno": "6"}, {"subno": "CH39006", "subname": "MASS TRANSFER LABORATORY", "ltp": "0-0-3 ", "crd": "2", "sub_type": "Depth", "grade": "A", "semno": "6"}, {"subno": "AI42001", "subname": "MACHINE LEARNING FOUNDATIONS AND APPLICATIONS", "ltp": "3-0-3", "crd": "5", "sub_type": "Elective I (PG)", "grade": "A", "semno": "7"}, {"subno": "BT40009", "subname": "BIOPROCESS TECHNOLOGY", "ltp": "3-1-0 ", "crd": "4", "sub_type": "Depth", "grade": "A", "semno": "7"}, {"subno": "BT47007", "subname": "PROJECT-I", "ltp": "0-0-0", "crd": "3", "sub_type": "Project-I", "grade": "B", "semno": "7"}, {"subno": "BT49001", "subname": "ENZYME TECHNOLOGY LABORATORY", "ltp": "0-0-3", "crd": "2", "sub_type": "Depth", "grade": "I", "semno": "7"}, {"subno": "EC60007", "subname": "", "ltp": "", "crd": "", "sub_type": "Elective II (PG)", "grade": "B", "semno": "7"}, {"subno": "MA41025", "subname": "REGRESSION AND TIME SERIES MODEL", "ltp": "3-1-0", "crd": "4", "sub_type": "IT", "grade": "A", "semno": "7"}, {"subno": "AI61002", "subname": "", "ltp": "", "crd": "", "sub_type": "Elective V (PG)", "grade": "B", "semno": "8"}, {"subno": "BT41012", "subname": "DOWNSTREAM PROCESSING", "ltp": "3-0-0 ", "crd": "3", "sub_type": "Elective IV", "grade": "A", "semno": "8"}, {"subno": "BT41022", "subname": "NEUROPHYSIOLOGY", "ltp": "3-1-0 ", "crd": "4", "sub_type": "Depth", "grade": "B", "semno": "8"}, {"subno": "BT47006", "subname": "PROJECT - PART 2", "ltp": "0-0-9 ", "crd": "6", "sub_type": "Project-II", "grade": "", "semno": "8"}, {"subno": "BT60004", "subname": "", "ltp": "", "crd": "", "sub_type": "Elective VI (PG)", "grade": "EX", "semno": "8"}, {"subno": "MM72335", "subname": "", "ltp": "", "crd": "", "sub_type": "Elective III", "grade": "EX", "semno": "8"}], [{"rollno": "17BT30025", "semno": "1", "sctscc": "23 - 23", "tcttcc": "23 - 23", "nccgsg": "8.78 - 8.78 - 8.78", "asctascc": "0 - 0", "acgasg": "0.00 - 0.00", "atctatcc": "0 - 0"}, {"rollno": "17BT30025", "semno": "2", "sctscc": "22 - 22", "tcttcc": "45 - 45", "nccgsg": "8.27 - 8.27 - 7.73", "asctascc": "0 - 0", "acgasg": "0.00 - 0.00", "atctatcc": "0 - 0"}, {"rollno": "17BT30025", "semno": "3", "sctscc": "22 - 22", "tcttcc": "67 - 67", "nccgsg": "8.21 - 8.21 - 8.09", "asctascc": "0 - 0", "acgasg": "0.00 - 0.00", "atctatcc": "0 - 0"}, {"rollno": "17BT30025", "semno": "4", "sctscc": "22 - 22", "tcttcc": "89 - 89", "nccgsg": "8.19 - 8.19 - 8.14", "asctascc": "0 - 0", "acgasg": "0.00 - 0.00", "atctatcc": "0 - 0"}, {"rollno": "17BT30025", "semno": "5", "sctscc": "23 - 23", "tcttcc": "112 - 112", "nccgsg": "8.25 - 8.25 - 8.48", "asctascc": "0 - 0", "acgasg": "0.00 - 0.00", "atctatcc": "0 - 0"}, {"rollno": "17BT30025", "semno": "6", "sctscc": "20 - 20", "tcttcc": "132 - 132", "nccgsg": "8.30 - 8.30 - 8.55", "asctascc": "0 - 0", "acgasg": "0.00 - 0.00", "atctatcc": "0 - 0"}, {"rollno": "17BT30025", "semno": "7", "sctscc": "19 - 19", "tcttcc": "151 - 151", "nccgsg": "8.34 - 8.34 - 8.68", "asctascc": "0 - 0", "acgasg": "0.00 - 0.00", "atctatcc": "0 - 0"}, {"rollno": "17BT30025", "semno": "8", "sctscc": "24 - 18", "tcttcc": "175 - 169", "nccgsg": "8.12 - 8.12 - 6.71", "asctascc": "0 - 0", "acgasg": "0.00 - 0.00", "atctatcc": "0 - 0"}]]}]